vex/__init__.py
vex/_version.py
vex/config.py
vex/exceptions.py
vex/main.py
vex/make.py
vex/options.py
vex/remove.py
vex/remove2.py
vex/run.py
vex/shell_config.py
vex/functional_tests/not_python
vex/shell_configs/bash
vex/shell_configs/fish
vex/shell_configs/fish.orig
vex/shell_configs/zsh
vex/shell_configs/zsh.orig
vex-0.0.19.data/scripts/vex
vex-0.0.19.dist-info/LICENSE
vex-0.0.19.dist-info/METADATA
vex-0.0.19.dist-info/WHEEL
vex-0.0.19.dist-info/entry_points.txt
vex-0.0.19.dist-info/top_level.txt
vex-0.0.19.dist-info/RECORD
