Metadata-Version: 2.1
Name: vex
Version: 0.0.19
Summary: Run commands in a virtualenv
Home-page: http://github.com/sashahart/vex
Author: Sasha Hart
Author-email: s@sashahart.net
License: MIT
Keywords: virtualenv virtualenvwrapper workon installation deployment
Platform: UNKNOWN
Classifier: Topic :: Utilities
Classifier: Topic :: Software Development
Classifier: Topic :: System :: Shells
Classifier: Intended Audience :: Developers
Classifier: Intended Audience :: System Administrators
Classifier: Environment :: Console
Classifier: License :: OSI Approved :: MIT License
Classifier: Development Status :: 3 - Alpha
Classifier: Operating System :: POSIX
Classifier: Operating System :: POSIX :: Linux
Classifier: Operating System :: Microsoft :: Windows
Classifier: Programming Language :: Python :: 3.4
Classifier: Programming Language :: Python :: 3.3
Classifier: Programming Language :: Python :: 3.2
Classifier: Programming Language :: Python :: 2.7
Classifier: Programming Language :: Python :: Implementation :: PyPy
Requires-Dist: virtualenv
